humble_chuck/__init__.py
humble_chuck/_modidx.py
humble_chuck/arc_gis.py
humble_chuck/core.py
humble_chuck/database.py
humble_chuck/delegation.py
humble_chuck/dependency.py
humble_chuck/display.py
humble_chuck/models.py
humble_chuck/multi_enum.py
humble_chuck-0.0.1.dist-info/LICENSE
humble_chuck-0.0.1.dist-info/METADATA
humble_chuck-0.0.1.dist-info/WHEEL
humble_chuck-0.0.1.dist-info/entry_points.txt
humble_chuck-0.0.1.dist-info/top_level.txt
humble_chuck-0.0.1.dist-info/RECORD
