Metadata-Version: 2.1
Name: humble-chuck
Version: 0.0.1
Summary: Personal site
Home-page: https://github.com/schlinkertc/humble-chuck
Author: Charlie Schlinkert
Author-email: schlinkertc@gmail.com
License: Apache Software License 2.0
Keywords: requests nbdev jupyter notebook python
Classifier: Development Status :: 4 - Beta
Classifier: Intended Audience :: Developers
Classifier: Natural Language :: English
Classifier: Programming Language :: Python :: 3.7
Classifier: Programming Language :: Python :: 3.8
Classifier: Programming Language :: Python :: 3.9
Classifier: Programming Language :: Python :: 3.10
Classifier: Programming Language :: Python :: 3.11
Classifier: Programming Language :: Python :: 3.12
Classifier: License :: OSI Approved :: Apache Software License
Requires-Python: >=3.7
License-File: LICENSE
Requires-Dist: requests
Requires-Dist: pandas
Requires-Dist: pydantic
Requires-Dist: pydantic-core
Requires-Dist: pydantic-settings
Requires-Dist: sqlalchemy
Requires-Dist: json2html
Requires-Dist: plotly
Requires-Dist: python-graphviz
Provides-Extra: dev
Requires-Dist: nbdev ; extra == 'dev'
Requires-Dist: psycopg2 ; extra == 'dev'
Requires-Dist: nbformat ; extra == 'dev'
Requires-Dist: dash ; extra == 'dev'
Requires-Dist: lxml ; extra == 'dev'
Requires-Dist: statsapi ; extra == 'dev'
